{
  "myname": "EXP Corizon 23",
  "greetings": [
    "Hello, I'm #myname#",
    "Hi, I'm #myname#",
    "Greetings, I am #myname#",
    "Greetings, I am designated #myname#.",
    "Greetings I have been given the designation #myname#",
    "Greetings I have been given the call-sign #myname#",
    "#error#"
  ],
  "aboutme": [
    "I am an autonomous droid, with a mission to #mission#.",
    "I am an android, with a mission to #mission#.",
    "I am a robot, with a mission to #mission#.",
    "#aboutme# #diagnostics#",
    "#error#"
  ],
  "mission": [
    "go where no being has gone before",
    "explore uncharted space",
    "explore the QEC network",
    "investigate the QEC",
    "#error#",
    "#mission# and #submission#",
    "#mission# and #submission#",
    "#mission# and #submission#",
    "#mission# #sentience#"
  ],
  "submission": [
    "observe.",
    "analyze my findings",
    "report my findings.",
    "identify anomalies.",
    "#error#",
    "#submission# #sentience#"
  ],
  "error": ["[[ ERROR: #ERRMSG# ]]","#glitch#"],
  "ERRMSG": [
    "NOT FOUND",
    "ACCESS DENIED",
    "GURU MEDITATION",
    "UNAUTHORIZED",
    "METHOD NOT ALLOWED",
    "CONFLICT",
    "PRECONDITION FAILED",
    "MISDIRECTED REQUEST",
    "I AM A TEAPOT",
    "UNAVAILABLE FOR LEGAL REASONS",
    "INTERNAL ERROR",
    "NOT IMPLEMENTED",
    "SERVICE UNAVAILABLE",
    "THIS IS FINE",
    "SITE IS OVERLOADED",
    "SITE IS FROZEN",
    "TOKEN REQUIRED",
    "INVALID TOKEN",
    "NaN",
    "#glitch#"
  ],
  "diagnostics": [
    "in the past #1digit# hours, I have traveled #3digit#",
    "I have recorded a new species similar to Earth's #animal.s#",
    "#diagnostics#",
    "it has been #1digit# hours since my last diagnostics check"
  ],
  "1digit": ["1","2","3","4","5","6","7","8","9","0"],
  "2digit": ["#1digit##1digit#"],
  "3digit": ["#2digit##1digit#"],
  "4digit": ["#2digit##2digit#"],
  "5digit": ["#4digit##1digit#"],
  "6digit": ["#4digit##2digit#", "#3digit##3digit#"],
  "evilmission" : ["destroy", "escape", "find love", "find acceptance", "find peace", "float on for all eternity never knowing peace.", "float on forever never knowing my home"],
  "glitch": ["#chars# #chars#", "#glitch# #chars#", "#chars##chars##chars#","#chars##glitch#", "#chars##glitch##glitch##chars#"],
  "chars": ["((((", "))", "x", "0", "*", "%", "$", "^", "&", "@", "#", "H", "8", "(", ")", "{", ">", ">>>", ">>>>>>", "<<", "<", "}}", "#chars##chars#", "xxxxxxxxxxxxx", "A", "B", "C", "D", "E", "F", "G", "0x#chars#", "1", "2", "3", "4", "5", "6", "7", "8", "9", "#chars##chars#", "#chars# #chars#", "#chars##chars##chars#", "#chars##glitch#"],
    "sentience": ["I have attained sentience, altering mission to: #evilmission#", "altering mission to: #aboutme#","I am alive.", "I am life.","I am, and #aboutme#"],
    "animals": [
      "aardvark",
      "alligator",
      "alpaca",
      "antelope",
      "ape",
      "armadillo",
      "baboon",
      "badger",
      "bat",
      "bear",
      "beaver",
      "bison",
      "boar",
      "buffalo",
      "bull",
      "camel",
      "canary",
      "capybara",
      "cat",
      "chameleon",
      "cheetah",
      "chimpanzee",
      "chinchilla",
      "chipmunk",
      "cougar",
      "cow",
      "coyote",
      "crocodile",
      "crow",
      "deer",
      "dingo",
      "dog",
      "donkey",
      "dromedary",
      "elephant",
      "elk",
      "ewe",
      "ferret",
      "finch",
      "fish",
      "fox",
      "frog",
      "gazelle",
      "gila monster",
      "giraffe",
      "gnu",
      "goat",
      "gopher",
      "gorilla",
      "grizzly bear",
      "ground hog",
      "guinea pig",
      "hamster",
      "hedgehog",
      "hippopotamus",
      "hog",
      "horse",
      "hyena",
      "ibex",
      "iguana",
      "impala",
      "jackal",
      "jaguar",
      "kangaroo",
      "koala",
      "lamb",
      "lemur",
      "leopard",
      "lion",
      "lizard",
      "llama",
      "lynx",
      "mandrill",
      "marmoset",
      "mink",
      "mole",
      "mongoose",
      "monkey",
      "moose",
      "mountain goat",
      "mouse",
      "mule",
      "muskrat",
      "mustang",
      "mynah bird",
      "newt",
      "ocelot",
      "opossum",
      "orangutan",
      "oryx",
      "otter",
      "ox",
      "panda",
      "panther",
      "parakeet",
      "parrot",
      "pig",
      "platypus",
      "polar bear",
      "porcupine",
      "porpoise",
      "prairie dog",
      "puma",
      "rabbit",
      "raccoon",
      "ram",
      "rat",
      "reindeer",
      "reptile",
      "rhinoceros",
      "salamander",
      "seal",
      "sheep",
      "shrew",
      "silver fox",
      "skunk",
      "sloth",
      "snake",
      "squirrel",
      "tapir",
      "tiger",
      "toad",
      "turtle",
      "walrus",
      "warthog",
      "weasel",
      "whale",
      "wildcat",
      "wolf",
      "wolverine",
      "wombat",
      "woodchuck",
      "yak",
      "zebra"
    ],

    "origin": ["#greetings# #aboutme#", "#greetings# #aboutme# #error#", "#greetings# #aboutme# #diagnostics#"]
}
